i64_parser/__init__.py
i64_parser/api.py
i64_parser/data.py
i64_parser/disasm.py
i64_parser/fixups.py
i64_parser/functions.py
i64_parser/globals.py
i64_parser/names.py
i64_parser/records.py
i64_parser/references.py
i64_parser/segments.py
i64_parser/strings.py
i64_parser/structures.py
i64_parser/types.py
i64_parser-1.0.2.dist-info/METADATA
i64_parser-1.0.2.dist-info/WHEEL
i64_parser-1.0.2.dist-info/entry_points.txt
i64_parser-1.0.2.dist-info/RECORD
