Metadata-Version: 2.4
Name: i64-parser
Version: 1.0.2
Summary: Python toolchain that reads IDA Pro .i64/.idb databases without launching IDA
Project-URL: Homepage, https://github.com/aidanqm/i64-parser
Project-URL: Repository, https://github.com/aidanqm/i64-parser
Project-URL: Issues, https://github.com/aidanqm/i64-parser/issues
Author-email: aidanqm <support@aidanqm.com>
License: Apache-2.0
Classifier: Development Status :: 4 - Beta
Classifier: Intended Audience :: Developers
Classifier: License :: OSI Approved :: Apache Software License
Classifier: Operating System :: OS Independent
Classifier: Programming Language :: Python :: 3
Classifier: Programming Language :: Python :: 3.9
Classifier: Programming Language :: Python :: 3.10
Classifier: Programming Language :: Python :: 3.11
Classifier: Programming Language :: Python :: 3.12
Classifier: Topic :: Security
Classifier: Topic :: Software Development :: Disassemblers
Classifier: Topic :: System :: Emulators
Requires-Python: >=3.9
Requires-Dist: capstone>=5.0.0
Requires-Dist: python-idb>=0.8.0
